scuEtherNeoJ/Etherscan.py
scuEtherNeoJ/__init__.py
scuEtherNeoJ-0.0.5.dist-info/LICENSE
scuEtherNeoJ-0.0.5.dist-info/METADATA
scuEtherNeoJ-0.0.5.dist-info/WHEEL
scuEtherNeoJ-0.0.5.dist-info/top_level.txt
scuEtherNeoJ-0.0.5.dist-info/RECORD
